LICENSE
README.md
batch_operations.py
comparison_tools.py
core_registry_tools.py
export_tools.py
kafka_schema_registry_unified_mcp.py
mcp_prompts.py
migration_tools.py
oauth_provider.py
pyproject.toml
schema_registry_common.py
statistics_tools.py
config-examples/README.md
demo/README.md
docs/README.md
docs/workflows/README.md
examples/README.md
glamaai/README.md
helm/README.md
helm/examples/README.md
inspector-tests/README.md
kubernetes/README.md
scripts/README.md
tests/README.md
iflow_mcp_aywengo_kafka_schema_registry_mcp-2.0.0.dist-info/METADATA
iflow_mcp_aywengo_kafka_schema_registry_mcp-2.0.0.dist-info/WHEEL
iflow_mcp_aywengo_kafka_schema_registry_mcp-2.0.0.dist-info/entry_points.txt
iflow_mcp_aywengo_kafka_schema_registry_mcp-2.0.0.dist-info/licenses/LICENSE
iflow_mcp_aywengo_kafka_schema_registry_mcp-2.0.0.dist-info/RECORD
