Metadata-Version: 2.4
Name: iflow-mcp_aywengo_kafka-schema-registry-mcp
Version: 2.0.0
Summary: A Model Context Protocol (MCP) server for Kafka Schema Registry - enables AI assistants to interact with Kafka schemas through a standardized interface
Project-URL: Homepage, https://github.com/aywengo/kafka-schema-reg-mcp
Project-URL: Repository, https://github.com/aywengo/kafka-schema-reg-mcp
Project-URL: Issues, https://github.com/aywengo/kafka-schema-reg-mcp/issues
Author: Kafka Schema Registry MCP Team
License: MIT
License-File: LICENSE
Requires-Python: >=3.10
Requires-Dist: aiofiles<25.0.0,>=23.2.1
Requires-Dist: aiohttp>=3.12.13
Requires-Dist: avro-python3>=1.10.0
Requires-Dist: cryptography>=45.0.0
Requires-Dist: fastmcp>=2.14.0
Requires-Dist: httpx>=0.25.2
Requires-Dist: jsonschema>=4.24.0
Requires-Dist: mcp>=1.23.0
Requires-Dist: pyjwt>=2.10.0
Requires-Dist: python-dotenv>=1.0.0
Requires-Dist: requests>=2.31.0
Provides-Extra: dev
Requires-Dist: black>=23.0.0; extra == 'dev'
Requires-Dist: mypy>=1.5.0; extra == 'dev'
Requires-Dist: pytest-asyncio>=0.21.0; extra == 'dev'
Requires-Dist: pytest>=7.4.0; extra == 'dev'
Requires-Dist: ruff>=0.1.0; extra == 'dev'
